cuvis_ai/__init__.py
cuvis_ai/anomaly/AbstractDetector.py
cuvis_ai/anomaly/RXDetector.py
cuvis_ai/anomaly/__init__.py
cuvis_ai/data/BaseDataSet.py
cuvis_ai/data/CuvisDataSet.py
cuvis_ai/data/LiveCuvisDataLoader.py
cuvis_ai/data/NumpyDataSet.py
cuvis_ai/data/OutputFormat.py
cuvis_ai/data/PublicDataSets.py
cuvis_ai/data/__init__.py
cuvis_ai/data/cocolabels.py
cuvis_ai/data/cuvis_dataset.py
cuvis_ai/data/metadata.py
cuvis_ai/data/utils_dataloader.py
cuvis_ai/deciders/__init__.py
cuvis_ai/deciders/base_decider.py
cuvis_ai/deciders/binary_decider.py
cuvis_ai/deciders/cascaded_decider.py
cuvis_ai/deciders/combining_decider.py
cuvis_ai/deciders/multiclass_decider.py
cuvis_ai/distance/__init__.py
cuvis_ai/distance/distance.py
cuvis_ai/node/Consumers.py
cuvis_ai/node/__init__.py
cuvis_ai/node/base.py
cuvis_ai/node/node.py
cuvis_ai/node/sklearn.py
cuvis_ai/node/skorch.py
cuvis_ai/node/torch.py
cuvis_ai/node/torchvision.py
cuvis_ai/node/wrap.py
cuvis_ai/pipeline/__init__.py
cuvis_ai/pipeline/executor.py
cuvis_ai/pipeline/graph.py
cuvis_ai/pipeline/meta_routing.py
cuvis_ai/pipeline/validator.py
cuvis_ai/preprocessor/__init__.py
cuvis_ai/preprocessor/sklearn_wrapped.py
cuvis_ai/supervised/__init__.py
cuvis_ai/supervised/sklearn_wrapped.py
cuvis_ai/supervised/skorch_supervised.py
cuvis_ai/test/__init__.py
cuvis_ai/test/test_numpy_utils.py
cuvis_ai/test/test_pipeline_graph.py
cuvis_ai/test/test_preprocessor_structural.py
cuvis_ai/test/test_serialization.py
cuvis_ai/test/test_unsupervised_structural.py
cuvis_ai/transformation/__init__.py
cuvis_ai/transformation/reflectance.py
cuvis_ai/transformation/torch_transformation.py
cuvis_ai/tv_transforms/Bandpass.py
cuvis_ai/tv_transforms/MultiBandpass.py
cuvis_ai/tv_transforms/NormalizeStdDev.py
cuvis_ai/tv_transforms/NormalizeToFloat.py
cuvis_ai/tv_transforms/WavelengthList.py
cuvis_ai/tv_transforms/__init__.py
cuvis_ai/unsupervised/__init__.py
cuvis_ai/unsupervised/sklearn_wrapped.py
cuvis_ai/utils/__init__.py
cuvis_ai-0.1.3.dist-info/licenses/LICENSE
cuvis_ai-0.1.3.dist-info/METADATA
cuvis_ai-0.1.3.dist-info/WHEEL
cuvis_ai-0.1.3.dist-info/top_level.txt
cuvis_ai-0.1.3.dist-info/RECORD
