Metadata-Version: 2.4
Name: cuvis_ai
Version: 0.1.3
Summary: The CUVIS.AI Toolset
Author-email: "Cubert GmbH, Ulm, Germany" <SDK@cubert-gmbh.com>
License: Apache License 2.0
Project-URL: Homepage, https://www.cubert-hyperspectral.com/
Project-URL: Repository, https://github.com/cubert-hyperspectral/cuvis.ai
Project-URL: Documentation, https://cubert-hyperspectral.github.io/cuvis.ai/
Project-URL: Changelog, https://github.com/cubert-hyperspectral/cuvis.ai/releases
Project-URL: Issues, https://github.com/cubert-hyperspectral/cuvis.ai/issues
Classifier: Intended Audience :: Developers
Classifier: License :: OSI Approved :: Apache Software License
Classifier: Programming Language :: Python :: 3
Classifier: Programming Language :: Python :: 3.10
Classifier: Programming Language :: Python :: 3.11
Classifier: Programming Language :: Python :: 3.12
Classifier: Programming Language :: Python :: 3.13
Classifier: Topic :: Scientific/Engineering :: Image Processing
Requires-Python: >=3.10
License-File: LICENSE
Requires-Dist: cuvis
Requires-Dist: setuptools; python_version >= "3.12"
Requires-Dist: torch
Requires-Dist: torchvision
Requires-Dist: scikit-learn
Requires-Dist: scikit-image
Requires-Dist: pycocotools
Requires-Dist: matplotlib
Requires-Dist: pyyaml
Requires-Dist: pytorch-lightning
Requires-Dist: skorch
Requires-Dist: imantics
Requires-Dist: networkx
Requires-Dist: opencv-python
Requires-Dist: torchvision
Requires-Dist: scikit-image
Requires-Dist: gdown
Requires-Dist: dataclass-wizard
Dynamic: license-file
